odoo/addons/company_dependent_attribute/README.rst
odoo/addons/company_dependent_attribute/__init__.py
odoo/addons/company_dependent_attribute/__manifest__.py
odoo/addons/company_dependent_attribute/i18n/company_dependent_attribute.pot
odoo/addons/company_dependent_attribute/i18n/hr.po
odoo/addons/company_dependent_attribute/i18n/pt.po
odoo/addons/company_dependent_attribute/models/__init__.py
odoo/addons/company_dependent_attribute/models/field.py
odoo/addons/company_dependent_attribute/readme/CONTRIBUTORS.rst
odoo/addons/company_dependent_attribute/readme/DESCRIPTION.rst
odoo/addons/company_dependent_attribute/static/description/icon.png
odoo/addons/company_dependent_attribute/static/description/index.html
odoo/addons/company_dependent_attribute/static/description/screen1.png
odoo/addons/company_dependent_attribute/views/field_view.xml
odoo12_addon_company_dependent_attribute-12.0.1.0.0.99.dev7.dist-info/METADATA
odoo12_addon_company_dependent_attribute-12.0.1.0.0.99.dev7.dist-info/WHEEL
odoo12_addon_company_dependent_attribute-12.0.1.0.0.99.dev7.dist-info/top_level.txt
odoo12_addon_company_dependent_attribute-12.0.1.0.0.99.dev7.dist-info/RECORD
